hearsavi/__init__.py
hearsavi/audio_cnn.py
hearsavi/savi.py
hearsavi/util.py
hear_savi-0.0.1.dist-info/LICENSE
hear_savi-0.0.1.dist-info/METADATA
hear_savi-0.0.1.dist-info/WHEEL
hear_savi-0.0.1.dist-info/top_level.txt
hear_savi-0.0.1.dist-info/RECORD
