Metadata-Version: 2.1
Name: hear-savi
Version: 0.0.1
Summary: An HEAR API for SAVI AudioCNN
Home-page: https://github.com/marl/hear-semav-embedding
Author: Sivan
Author-email: siwen.d@columbia.edu
License: LICENSE
Project-URL: Bug Tracker, https://github.com/marl/hear-semav-embedding/issues
Project-URL: Source Code, https://github.com/marl/hear-semav-embedding
Requires-Python: >=3.7
License-File: LICENSE
Requires-Dist: librosa
Requires-Dist: typing
Requires-Dist: scikit-image
Requires-Dist: numba
Requires-Dist: numpy
Requires-Dist: torch
Requires-Dist: torchaudio (==0.11.0)
Provides-Extra: dev
Requires-Dist: pre-commit ; extra == 'dev'
Requires-Dist: black ; extra == 'dev'
Requires-Dist: pytest ; extra == 'dev'
Requires-Dist: pytest-cov ; extra == 'dev'
Requires-Dist: pytest-env ; extra == 'dev'
Provides-Extra: test
Requires-Dist: pytest ; extra == 'test'
Requires-Dist: pytest-cov ; extra == 'test'
Requires-Dist: pytest-env ; extra == 'test'
